Workbook

Sheet MENU
B2: 🧾 ORGANIZADOR DO IMPOSTO DE RENDA
B3: Reúna em um só lugar tudo o que você precisa para a declaração do IRPF
C5: Comece por aqui:
C7: 👤 1. DADOS DO TITULAR | E7: 🏦 2. INFORMES BANCÁRIOS
C8: Nome, CPF, endereço e contatos | E8: Saldos e rendimentos por banco
C11: 💰 3. ENTRADAS DO ANO | E11: 🩺 4. DESPESAS DEDUTÍVEIS
C12: Holerites, freelas e outras receitas | E12: Saúde, educação, previdência...
C15: 📊 5. RESUMO E PENDÊNCIAS
C16: Totais, gráfico e checklist
C19: 🔗 LINKS RÁPIDOS (Receita Federal)
C20: ▸ Meu Imposto de Renda (página oficial)
C21: ▸ Fazer a declaração
C22: ▸ Baixar o programa da declaração (PGD)
C23: ▸ Orientações de preenchimento
C24: ▸ Consultar restituição
C26: Os valores já preenchidos são fictícios, só de exemplo. Apague e coloque os seus.

Sheet TITULAR
B2: 👤 1. DADOS DO TITULAR
B3: Preencha os dados da pessoa física que vai declarar
B5: ◀ VOLTAR AO MENU | D5: Você preenche | E5: Calculado
B7: NOME COMPLETO | D7: MARIA EXEMPLO DA SILVA
B8: CPF (só números) | D8: 12345678909 | E8: ← fica 123.456.789-09
B9: DATA DE NASCIMENTO | D9: 31121
B10: TÍTULO DE ELEITOR | D10: 123456789012
B11: OCUPAÇÃO | D11: Professora
B12: CÔNJUGE | D12: JOÃO EXEMPLO DA SILVA
B13: ENDEREÇO (rua e número) | D13: Rua das Palmeiras, 123
B14: CIDADE | D14: São Paulo
B15: UF | D15: SP
B16: CEP (só números) | D16: 1234000
B17: TELEFONE (DDD + número) | D17: 1133334444
B18: CELULAR (DDD + número) | D18: 11988887777
B19: E-MAIL | D19: maria.exemplo@email.com
B20: HOUVE ALTERAÇÃO DESDE A ÚLTIMA ENTREGA? | D20: NÃO
B21: CÔNJUGE É DEPENDENTE? | D21: NÃO
B22: RESIDENTE NO EXTERIOR? | D22: NÃO
B24: CALCULADOS AUTOMATICAMENTE
B25: IDADE | D25: =IF(D9="","",DATEDIF(D9,TODAY(),"Y")&" anos") -> 41 anos
B26: ENDEREÇO ABREVIADO | D26: =TRIM(SUBSTITUTE(SUBSTITUTE(SUBSTITUTE(SUBSTITUTE(D13,"Rua ","R. "),"Avenida ","Av. "),"Travessa ","Tv. "),"Alameda ","Al. ")) -> R. das Palmeiras, 123
B27: CPF FORMATADO (texto) | D27: =TEXT(D8,"000\.000\.000-00") -> 123.456.789-09
B28: ENVIAR E-MAIL AO CONTADOR | D28: =HYPERLINK("mailto:"&D20&"?subject="&"Documentos IRPF - "&D7,"✉ Abrir e-mail com assunto pronto") -> ✉ Abrir e-mail com assunto pronto

Sheet INFORMES
B2: 🏦 2. INFORMES DE RENDIMENTOS BANCÁRIOS
B3: Um banco por linha: saldos em 31/12 e rendimentos do ano, conforme o informe de cada instituição
B5: ◀ VOLTAR AO MENU | E5: Você preenche | F5: Calculado
B7: Nº | C7: BANCO | D7: TIPO DE CONTA | E7: SALDO 31/12 ANO ANTERIOR | F7: SALDO 31/12 ANO-BASE | G7: RENDIMENTOS NO ANO | H7: INFORME RECEBIDO? | I7: ARQUIVO DO INFORME
B8: 1 | C8: 260 - Nubank | D8: Conta corrente | E8: 1850 | F8: 2340.5 | G8: 0 | H8: SIM | I8: informe_nubank.pdf
B9: 2 | C9: 260 - Nubank | D9: Investimentos (renda fixa) | E9: 5000 | F9: 6120.3 | G9: 520.3 | H9: SIM | I9: informe_nubank.pdf
B10: 3 | C10: 104 - Caixa Econômica Federal | D10: Poupança | E10: 3200 | F10: 3415.8 | G10: 215.8 | H10: NÃO
B11: 4 | C11: 77 - Banco Inter | D11: Conta corrente | E11: 410 | F11: 980.25 | G11: 0 | H11: SIM | I11: informe_inter.pdf
B12: 5
B13: 6
B14: 7
B15: 8
B16: 9
B17: 10
B18: 11
B19: 12
C20: TOTAL | E20: =SUM(E8:E19) -> 10460 | F20: =SUM(F8:F19) -> 12856.85 | G20: =SUM(G8:G19) -> 736.1
C22: Informe pendente aparece em vermelho. O nome do arquivo ajuda a achar o PDF na hora de declarar.

Sheet NOTAS
B2: 💰 3. ENTRADAS DO ANO (HOLERITES E OUTRAS RECEITAS)
B3: Lance cada entrada mês a mês. O mês e o total são calculados sozinhos
B5: ◀ VOLTAR AO MENU | E5: Você preenche | F5: Calculado
B7: DATA | C7: MÊS | D7: CATEGORIA | E7: FONTE PAGADORA | F7: CNPJ/CPF DA FONTE | G7: VALOR BRUTO | H7: IR RETIDO NA FONTE | I7: OBSERVAÇÃO
B8: 45662 | C8: =IF(B8="","",CHOOSE(MONTH(B8),"Jan","Fev","Mar","Abr","Mai","Jun","Jul","Ago","Set","Out","Nov","Dez")) -> Jan | D8: HOLERITE | E8: Escola Exemplo Ltda | F8: 00.000.000/0001-00 | G8: 3500 | H8: 180.4
B9: 45693 | C9: =IF(B9="","",CHOOSE(MONTH(B9),"Jan","Fev","Mar","Abr","Mai","Jun","Jul","Ago","Set","Out","Nov","Dez")) -> Fev | D9: HOLERITE | E9: Escola Exemplo Ltda | F9: 00.000.000/0001-00 | G9: 3500 | H9: 180.4
B10: 45708 | C10: =IF(B10="","",CHOOSE(MONTH(B10),"Jan","Fev","Mar","Abr","Mai","Jun","Jul","Ago","Set","Out","Nov","Dez")) -> Fev | D10: FREELANCE | E10: Cliente Exemplo | F10: 000.000.000-00 | G10: 800 | H10: 0 | I10: Curso de Excel
B11: 45721 | C11: =IF(B11="","",CHOOSE(MONTH(B11),"Jan","Fev","Mar","Abr","Mai","Jun","Jul","Ago","Set","Out","Nov","Dez")) -> Mar | D11: HOLERITE | E11: Escola Exemplo Ltda | F11: 00.000.000/0001-00 | G11: 3500 | H11: 180.4
B12: 45752 | C12: =IF(B12="","",CHOOSE(MONTH(B12),"Jan","Fev","Mar","Abr","Mai","Jun","Jul","Ago","Set","Out","Nov","Dez")) -> Abr | D12: HOLERITE | E12: Escola Exemplo Ltda | F12: 00.000.000/0001-00 | G12: 3650 | H12: 198.2 | I12: Reajuste
B13: 45765 | C13: =IF(B13="","",CHOOSE(MONTH(B13),"Jan","Fev","Mar","Abr","Mai","Jun","Jul","Ago","Set","Out","Nov","Dez")) -> Abr | D13: ALUGUEL | E13: Inquilino Exemplo | F13: 000.000.000-00 | G13: 1200 | H13: 0 | I13: Apto 12
B14: 45782 | C14: =IF(B14="","",CHOOSE(MONTH(B14),"Jan","Fev","Mar","Abr","Mai","Jun","Jul","Ago","Set","Out","Nov","Dez")) -> Mai | D14: HOLERITE | E14: Escola Exemplo Ltda | F14: 00.000.000/0001-00 | G14: 3650 | H14: 198.2
B15: 45813 | C15: =IF(B15="","",CHOOSE(MONTH(B15),"Jan","Fev","Mar","Abr","Mai","Jun","Jul","Ago","Set","Out","Nov","Dez")) -> Jun | D15: HOLERITE | E15: Escola Exemplo Ltda | F15: 00.000.000/0001-00 | G15: 3650 | H15: 198.2
C16: =IF(B16="","",CHOOSE(MONTH(B16),"Jan","Fev","Mar","Abr","Mai","Jun","Jul","Ago","Set","Out","Nov","Dez"))
C17: =IF(B17="","",CHOOSE(MONTH(B17),"Jan","Fev","Mar","Abr","Mai","Jun","Jul","Ago","Set","Out","Nov","Dez"))
C18: =IF(B18="","",CHOOSE(MONTH(B18),"Jan","Fev","Mar","Abr","Mai","Jun","Jul","Ago","Set","Out","Nov","Dez"))
C19: =IF(B19="","",CHOOSE(MONTH(B19),"Jan","Fev","Mar","Abr","Mai","Jun","Jul","Ago","Set","Out","Nov","Dez"))
C20: =IF(B20="","",CHOOSE(MONTH(B20),"Jan","Fev","Mar","Abr","Mai","Jun","Jul","Ago","Set","Out","Nov","Dez"))
C21: =IF(B21="","",CHOOSE(MONTH(B21),"Jan","Fev","Mar","Abr","Mai","Jun","Jul","Ago","Set","Out","Nov","Dez"))
C22: =IF(B22="","",CHOOSE(MONTH(B22),"Jan","Fev","Mar","Abr","Mai","Jun","Jul","Ago","Set","Out","Nov","Dez"))
C23: =IF(B23="","",CHOOSE(MONTH(B23),"Jan","Fev","Mar","Abr","Mai","Jun","Jul","Ago","Set","Out","Nov","Dez"))
C24: =IF(B24="","",CHOOSE(MONTH(B24),"Jan","Fev","Mar","Abr","Mai","Jun","Jul","Ago","Set","Out","Nov","Dez"))
C25: =IF(B25="","",CHOOSE(MONTH(B25),"Jan","Fev","Mar","Abr","Mai","Jun","Jul","Ago","Set","Out","Nov","Dez"))
C26: =IF(B26="","",CHOOSE(MONTH(B26),"Jan","Fev","Mar","Abr","Mai","Jun","Jul","Ago","Set","Out","Nov","Dez"))
C27: =IF(B27="","",CHOOSE(MONTH(B27),"Jan","Fev","Mar","Abr","Mai","Jun","Jul","Ago","Set","Out","Nov","Dez"))
... C67: =IF(B67="","",CHOOSE(MONTH(B67),"Jan","Fev","Mar","Abr","Mai","Jun","Jul","Ago","Set","Out","Nov","Dez"))
F68: TOTAL | G68: =SUM(G8:G67) -> 23450 | H68: =SUM(H8:H67) -> 1135.8

Sheet DEDUCOES
B2: 🩺 4. DESPESAS DEDUTÍVEIS
B3: Guarde aqui cada despesa que pode ser deduzida e o comprovante correspondente
B5: ◀ VOLTAR AO MENU | E5: Você preenche | F5: Calculado
B7: DATA | C7: TIPO DE DEDUÇÃO | D7: BENEFICIÁRIO | E7: PRESTADOR / INSTITUIÇÃO | F7: CNPJ/CPF DO PRESTADOR | G7: VALOR PAGO | H7: TEM COMPROVANTE? | I7: ARQUIVO DO COMPROVANTE
B8: 45698 | C8: SAÚDE | D8: Titular | E8: Clínica Exemplo | F8: 00.000.000/0001-00 | G8: 350 | H8: SIM | I8: recibo_clinica_fev.pdf
B9: 45717 | C9: EDUCAÇÃO | D9: Dependente | E9: Colégio Exemplo | F9: 00.000.000/0001-00 | G9: 980 | H9: SIM | I9: mensalidade_mar.pdf
B10: 45738 | C10: SAÚDE | D10: Dependente | E10: Dentista Exemplo | F10: 000.000.000-00 | G10: 600 | H10: NÃO
B11: 45792 | C11: PREVIDÊNCIA PRIVADA (PGBL) | D11: Titular | E11: Seguradora Exemplo | F11: 00.000.000/0001-00 | G11: 400 | H11: SIM | I11: pgbl_2025.pdf
F48: TOTAL | G48: =SUM(G8:G47) -> 2330
B50: Os limites de dedução mudam a cada ano: confira as regras atuais nas orientações da Receita Federal (link no MENU).

Sheet RESUMO
B2: 📊 5. RESUMO E PENDÊNCIAS
B3: Tudo calculado a partir das outras abas. Nada para preencher aqui
B5: ◀ VOLTAR AO MENU
B7: TITULAR
B8: Nome | C8: =TITULAR!D7 -> MARIA EXEMPLO DA SILVA
B9: CPF | C9: =TITULAR!D8 -> 12345678909
B11: ENTRADAS POR CATEGORIA
B12: CATEGORIA | C12: TOTAL NO ANO | E12: BANCOS
B13: HOLERITE | C13: =SUMIF(NOTAS!$D$8:$D$67,B13,NOTAS!$G$8:$G$67) -> 21450 | E13: Saldo total 31/12 ano anterior | F13: =INFORMES!E20 -> 10460
B14: PRÓ-LABORE / CNPJ | C14: =SUMIF(NOTAS!$D$8:$D$67,B14,NOTAS!$G$8:$G$67) -> 0 | E14: Saldo total 31/12 ano-base | F14: =INFORMES!F20 -> 12856.85
B15: FREELANCE | C15: =SUMIF(NOTAS!$D$8:$D$67,B15,NOTAS!$G$8:$G$67) -> 800 | E15: Rendimentos no ano | F15: =INFORMES!G20 -> 736.1
B16: ALUGUEL | C16: =SUMIF(NOTAS!$D$8:$D$67,B16,NOTAS!$G$8:$G$67) -> 1200 | E16: Contas cadastradas | F16: =COUNTA(INFORMES!C8:C19) -> 4
B17: 13º SALÁRIO | C17: =SUMIF(NOTAS!$D$8:$D$67,B17,NOTAS!$G$8:$G$67) -> 0 | E17: DEDUÇÕES POR TIPO
B18: FÉRIAS | C18: =SUMIF(NOTAS!$D$8:$D$67,B18,NOTAS!$G$8:$G$67) -> 0 | E18: TIPO | F18: TOTAL
B19: OUTROS | C19: =SUMIF(NOTAS!$D$8:$D$67,B19,NOTAS!$G$8:$G$67) -> 0 | E19: SAÚDE | F19: =SUMIF(DEDUCOES!$C$8:$C$47,E19,DEDUCOES!$G$8:$G$47) -> 950
B20: TOTAL DE ENTRADAS | C20: =SUM(C13:C19) -> 23450 | E20: EDUCAÇÃO | F20: =SUMIF(DEDUCOES!$C$8:$C$47,E20,DEDUCOES!$G$8:$G$47) -> 980
B21: IR RETIDO NA FONTE | C21: =NOTAS!H68 -> 1135.8 | E21: PREVIDÊNCIA PRIVADA (PGBL) | F21: =SUMIF(DEDUCOES!$C$8:$C$47,E21,DEDUCOES!$G$8:$G$47) -> 400
E22: PENSÃO ALIMENTÍCIA | F22: =SUMIF(DEDUCOES!$C$8:$C$47,E22,DEDUCOES!$G$8:$G$47) -> 0
B23: ✅ CHECKLIST DE PENDÊNCIAS | E23: INSS AUTÔNOMO | F23: =SUMIF(DEDUCOES!$C$8:$C$47,E23,DEDUCOES!$G$8:$G$47) -> 0
B24: Dados do titular incompletos | C24: =COUNTBLANK(TITULAR!D7:D22) -> 0 | D24: =IF(C24=0,"✔ OK","⚠ Resolver") -> ✔ OK | E24: OUTRAS | F24: =SUMIF(DEDUCOES!$C$8:$C$47,E24,DEDUCOES!$G$8:$G$47) -> 0
B25: Informes bancários não recebidos | C25: =COUNTIF(INFORMES!H8:H19,"NÃO") -> 1 | D25: =IF(C25=0,"✔ OK","⚠ Resolver") -> ⚠ Resolver | E25: TOTAL DE DEDUÇÕES | F25: =SUM(F19:F24) -> 2330
B26: Despesas sem comprovante | C26: =COUNTIF(DEDUCOES!H8:H47,"NÃO") -> 1 | D26: =IF(C26=0,"✔ OK","⚠ Resolver") -> ⚠ Resolver
B29: ENTRADAS POR MÊS
B30: MÊS | C30: VALOR BRUTO
B31: Jan | C31: =SUMPRODUCT((MONTH(NOTAS!$B$8:$B$67)=1)*(NOTAS!$B$8:$B$67<>"")*NOTAS!$G$8:$G$67) -> 3500
B32: Fev | C32: =SUMPRODUCT((MONTH(NOTAS!$B$8:$B$67)=2)*(NOTAS!$B$8:$B$67<>"")*NOTAS!$G$8:$G$67) -> 4300
B33: Mar | C33: =SUMPRODUCT((MONTH(NOTAS!$B$8:$B$67)=3)*(NOTAS!$B$8:$B$67<>"")*NOTAS!$G$8:$G$67) -> 3500
B34: Abr | C34: =SUMPRODUCT((MONTH(NOTAS!$B$8:$B$67)=4)*(NOTAS!$B$8:$B$67<>"")*NOTAS!$G$8:$G$67) -> 4850
B35: Mai | C35: =SUMPRODUCT((MONTH(NOTAS!$B$8:$B$67)=5)*(NOTAS!$B$8:$B$67<>"")*NOTAS!$G$8:$G$67) -> 3650
B36: Jun | C36: =SUMPRODUCT((MONTH(NOTAS!$B$8:$B$67)=6)*(NOTAS!$B$8:$B$67<>"")*NOTAS!$G$8:$G$67) -> 3650
B37: Jul | C37: =SUMPRODUCT((MONTH(NOTAS!$B$8:$B$67)=7)*(NOTAS!$B$8:$B$67<>"")*NOTAS!$G$8:$G$67) -> 0
B38: Ago | C38: =SUMPRODUCT((MONTH(NOTAS!$B$8:$B$67)=8)*(NOTAS!$B$8:$B$67<>"")*NOTAS!$G$8:$G$67) -> 0
B39: Set | C39: =SUMPRODUCT((MONTH(NOTAS!$B$8:$B$67)=9)*(NOTAS!$B$8:$B$67<>"")*NOTAS!$G$8:$G$67) -> 0
B40: Out | C40: =SUMPRODUCT((MONTH(NOTAS!$B$8:$B$67)=10)*(NOTAS!$B$8:$B$67<>"")*NOTAS!$G$8:$G$67) -> 0
B41: Nov | C41: =SUMPRODUCT((MONTH(NOTAS!$B$8:$B$67)=11)*(NOTAS!$B$8:$B$67<>"")*NOTAS!$G$8:$G$67) -> 0
B42: Dez | C42: =SUMPRODUCT((MONTH(NOTAS!$B$8:$B$67)=12)*(NOTAS!$B$8:$B$67<>"")*NOTAS!$G$8:$G$67) -> 0

Sheet TABELAS
A1: BANCOS | B1: TIPO DE CONTA | C1: CATEGORIA DE ENTRADA | D1: TIPO DE DEDUÇÃO | E1: BENEFICIÁRIO | F1: SIM/NÃO | G1: UF
A2: 1 - Banco do Brasil | B2: Conta corrente | C2: HOLERITE | D2: SAÚDE | E2: Titular | F2: SIM | G2: AC
A3: 102 - XP Investimentos CCTVM S.A. | B3: Poupança | C3: PRÓ-LABORE / CNPJ | D3: EDUCAÇÃO | E3: Dependente | F3: NÃO | G3: AL
A4: 104 - Caixa Econômica Federal | B4: Investimentos (renda fixa) | C4: FREELANCE | D4: PREVIDÊNCIA PRIVADA (PGBL) | E4: Cônjuge | G4: AP
A5: 119 - Banco Western Union do Brasil | B5: Investimentos (renda variável) | C5: ALUGUEL | D5: PENSÃO ALIMENTÍCIA | G5: AM
A6: 184 - Banco Itaú BBA S.A. | B6: Previdência privada | C6: 13º SALÁRIO | D6: INSS AUTÔNOMO | G6: BA
A7: 197 - Stone Pagamentos | C7: FÉRIAS | D7: OUTRAS | G7: CE
A8: 208 - Banco BTG Pactual | C8: OUTROS | G8: DF
A9: 212 - Banco Original | G9: ES
A10: 218 - Banco Bonsucesso | G10: GO
A11: 229 - Banco Cruzeiro do Sul | G11: MA
A12: 237 - Banco Bradesco | G12: MT
A13: 24 - Banco de Pernambuco | G13: MS
A14: 241 - Banco Clássico | G14: MG
A15: 250 - Banco de Crédito e Varejo (BCV) | G15: PA
A16: 260 - Nubank | G16: PB
A17: 29 - Banco do Estado do Rio de Janeiro | G17: PR
A18: 290 - PagBank | G18: PE
A19: 3 - Banco da Amazônia | G19: PI
A20: 33 - Banco Santander | G20: RJ
... A28: 422 - Banco Safra | G28: TO
A29: 44 - Banco BVA
A30: 464 - Banco Sumitomo Mitsui Brasileiro
A31: 477 - Citibank
A32: 600 - Banco Luso Brasileiro
A33: 604 - Banco Industrial do Brasil
A34: 610 - Banco VR
A35: 62 - Hipercard Banco Múltiplo
A36: 634 - Banco Triângulo
A37: 65 - Banco Lemon
A38: 654 - Banco AJ Renner
A39: 655 - Banco Votorantim
A40: 66 - Banco Morgan Stanley
... A51: 82 - Banco Topázio
